[{"course_id": "C002", "concept_name": "Recursion", "n": 409, "fails": 349, "fail_rate": 85.33, "course_name": "Python Programming"}, {"course_id": "C007", "concept_name": "Overfitting & Regularization", "n": 5, "fails": 3, "fail_rate": 60.0, "course_name": "Cybersecurity Essentials"}, {"course_id": "C007", "concept_name": "Model Evaluation", "n": 2, "fails": 1, "fail_rate": 50.0, "course_name": "Cybersecurity Essentials"}, {"course_id": "C001", "concept_name": "Joins & Merges", "n": 446, "fails": 215, "fail_rate": 48.21, "course_name": "Data Analytics Fundamentals"}, {"course_id": "C006", "concept_name": "Overfitting & Regularization", "n": 435, "fails": 205, "fail_rate": 47.13, "course_name": "Machine Learning Basics"}, {"course_id": "C005", "concept_name": "Funnel Analytics", "n": 349, "fails": 164, "fail_rate": 46.99, "course_name": "Digital Marketing"}, {"course_id": "C005", "concept_name": "SEO Basics", "n": 348, "fails": 162, "fail_rate": 46.55, "course_name": "Digital Marketing"}, {"course_id": "C005", "concept_name": "Content Strategy", "n": 348, "fails": 157, "fail_rate": 45.11, "course_name": "Digital Marketing"}, {"course_id": "C005", "concept_name": "Paid Ads", "n": 348, "fails": 151, "fail_rate": 43.39, "course_name": "Digital Marketing"}, {"course_id": "C007", "concept_name": "Clustering", "n": 4, "fails": 1, "fail_rate": 25.0, "course_name": "Cybersecurity Essentials"}, {"course_id": "C007", "concept_name": "Regression", "n": 4, "fails": 1, "fail_rate": 25.0, "course_name": "Cybersecurity Essentials"}, {"course_id": "C003", "concept_name": "Responsive Design", "n": 217, "fails": 49, "fail_rate": 22.58, "course_name": "Web Development"}, {"course_id": "C003", "concept_name": "JavaScript DOM", "n": 214, "fails": 46, "fail_rate": 21.5, "course_name": "Web Development"}, {"course_id": "C003", "concept_name": "HTML & Semantics", "n": 221, "fails": 45, "fail_rate": 20.36, "course_name": "Web Development"}, {"course_id": "C003", "concept_name": "HTTP & APIs", "n": 230, "fails": 46, "fail_rate": 20.0, "course_name": "Web Development"}, {"course_id": "C004", "concept_name": "Prototyping", "n": 276, "fails": 50, "fail_rate": 18.12, "course_name": "UI/UX Design"}, {"course_id": "C004", "concept_name": "Color Theory", "n": 266, "fails": 47, "fail_rate": 17.67, "course_name": "UI/UX Design"}, {"course_id": "C003", "concept_name": "CSS Layout", "n": 222, "fails": 39, "fail_rate": 17.57, "course_name": "Web Development"}, {"course_id": "C006", "concept_name": "Regression", "n": 437, "fails": 75, "fail_rate": 17.16, "course_name": "Machine Learning Basics"}, {"course_id": "C001", "concept_name": "Descriptive Statistics", "n": 428, "fails": 72, "fail_rate": 16.82, "course_name": "Data Analytics Fundamentals"}]